NStructAnaly/Comparision.py
NStructAnaly/Computer.py
NStructAnaly/DynamicResponse.py
NStructAnaly/FiniteElementDivisor.py
NStructAnaly/FirstOrderResponse.py
NStructAnaly/Functions.py
NStructAnaly/Input.py
NStructAnaly/Loads.py
NStructAnaly/Model.py
NStructAnaly/Model_Parametrization.py
NStructAnaly/SecondOrderResponse.py
NStructAnaly/Sensitivity.py
NStructAnaly/StructuralElements.py
NStructAnaly/__init__.py
NStructAnaly/config.py
NStructAnaly/main.py
nstructanaly-0.1.9.dist-info/licenses/LICENSE.txt
nstructanaly-0.1.9.dist-info/METADATA
nstructanaly-0.1.9.dist-info/WHEEL
nstructanaly-0.1.9.dist-info/top_level.txt
nstructanaly-0.1.9.dist-info/RECORD
