Metadata-Version: 2.4
Name: NStructAnaly
Version: 0.1.9
Summary: A Python package for Structural analysis
Home-page: https://github.com/AakashR003/Frames
Author: Aakash
Author-email: Aakash <aakashravichandran22@gmail.com>
License: MIT
Project-URL: Homepage, https://github.com/AakashR003/Frames
Requires-Python: >=3.7
License-File: LICENSE.txt
Requires-Dist: numpy>=1.20.0
Requires-Dist: scipy>=1.7.0
Requires-Dist: matplotlib>=3.4.0
Provides-Extra: dev
Requires-Dist: pytest>=7.0; extra == "dev"
Requires-Dist: twine>=4.0; extra == "dev"
Dynamic: license-file
